blop/__init__.py
blop/_version.py
blop/agent.py
blop/dofs.py
blop/objectives.py
blop/plans.py
blop/plotting.py
blop/bayesian/__init__.py
blop/bayesian/kernels.py
blop/bayesian/models.py
blop/bayesian/acquisition/__init__.py
blop/bayesian/acquisition/analytic.py
blop/bayesian/acquisition/config.yml
blop/bayesian/acquisition/monte_carlo.py
blop/de/__init__.py
blop/de/de_opt_utils.py
blop/de/de_optimization.py
blop/de/hardware_flyer.py
blop/digestion/__init__.py
blop/digestion/tests.py
blop/sim/__init__.py
blop/sim/beamline.py
blop/sim/handlers.py
blop/tests/__init__.py
blop/tests/conftest.py
blop/tests/test_acqfs.py
blop/tests/test_agents.py
blop/tests/test_dofs.py
blop/tests/test_pareto.py
blop/tests/test_sims.py
blop/utils/__init__.py
blop/utils/functions.py
blop/utils/prepare_re_env.py
bloptools-0.7.1.dist-info/METADATA
bloptools-0.7.1.dist-info/WHEEL
bloptools-0.7.1.dist-info/licenses/LICENSE
bloptools-0.7.1.dist-info/RECORD
