Metadata-Version: 2.3
Name: bloptools
Version: 0.7.1
Summary: Beamline optimization with machine learning
Project-URL: Homepage, https://github.com/NSLS-II/blop
Project-URL: Documentation, https://nsls-ii.github.io/blop
Project-URL: Bug Reports, https://github.com/NSLS-II/blop/issues
Author-email: Brookhaven National Laboratory <tmorris@bnl.gov>
Maintainer-email: Brookhaven National Laboratory <tmorris@bnl.gov>
License-File: LICENSE
Classifier: Development Status :: 4 - Beta
Classifier: License :: OSI Approved :: BSD License
Classifier: Programming Language :: Python :: 3 :: Only
Classifier: Programming Language :: Python :: 3.9
Classifier: Programming Language :: Python :: 3.10
Classifier: Programming Language :: Python :: 3.11
Classifier: Topic :: Scientific/Engineering :: Physics
Requires-Python: >=3.9
Requires-Dist: area-detector-handlers
Requires-Dist: bluesky
Requires-Dist: botorch
Requires-Dist: databroker
Requires-Dist: gpytorch
Requires-Dist: h5py
Requires-Dist: matplotlib
Requires-Dist: numpy<2
Requires-Dist: ophyd
Requires-Dist: ortools
Requires-Dist: scipy
Requires-Dist: tables
Requires-Dist: torch
Provides-Extra: dev
Requires-Dist: black; extra == 'dev'
Requires-Dist: coverage; extra == 'dev'
Requires-Dist: flake8; extra == 'dev'
Requires-Dist: furo; extra == 'dev'
Requires-Dist: ipython; extra == 'dev'
Requires-Dist: isort; extra == 'dev'
Requires-Dist: jupyter; extra == 'dev'
Requires-Dist: matplotlib; extra == 'dev'
Requires-Dist: nbsphinx; extra == 'dev'
Requires-Dist: nbstripout; extra == 'dev'
Requires-Dist: numpydoc; extra == 'dev'
Requires-Dist: pandoc; extra == 'dev'
Requires-Dist: pre-commit; extra == 'dev'
Requires-Dist: pre-commit-hooks; extra == 'dev'
Requires-Dist: pytest; extra == 'dev'
Requires-Dist: pytest-codecov; extra == 'dev'
Requires-Dist: sphinx; extra == 'dev'
Requires-Dist: sphinx-copybutton; extra == 'dev'
Requires-Dist: sphinx-rtd-theme; extra == 'dev'
Requires-Dist: twine; extra == 'dev'
Provides-Extra: gui
Requires-Dist: nicegui; extra == 'gui'
Provides-Extra: napari
Requires-Dist: napari; extra == 'napari'
Provides-Extra: sirepo
Requires-Dist: sirepo-bluesky; extra == 'sirepo'
